azure/cli/testsdk/__init__.py
azure/cli/testsdk/base.py
azure/cli/testsdk/checkers.py
azure/cli/testsdk/constants.py
azure/cli/testsdk/decorators.py
azure/cli/testsdk/exceptions.py
azure/cli/testsdk/patches.py
azure/cli/testsdk/preparers.py
azure/cli/testsdk/reverse_dependency.py
azure/cli/testsdk/utilities.py
azure/cli/testsdk/scenario_tests/__init__.py
azure/cli/testsdk/scenario_tests/base.py
azure/cli/testsdk/scenario_tests/config.py
azure/cli/testsdk/scenario_tests/const.py
azure/cli/testsdk/scenario_tests/decorators.py
azure/cli/testsdk/scenario_tests/exceptions.py
azure/cli/testsdk/scenario_tests/patches.py
azure/cli/testsdk/scenario_tests/preparers.py
azure/cli/testsdk/scenario_tests/recording_processors.py
azure/cli/testsdk/scenario_tests/utilities.py
azure_cli_testsdk-0.3.0.dist-info/LICENSE.txt
azure_cli_testsdk-0.3.0.dist-info/METADATA
azure_cli_testsdk-0.3.0.dist-info/WHEEL
azure_cli_testsdk-0.3.0.dist-info/top_level.txt
azure_cli_testsdk-0.3.0.dist-info/RECORD
