Metadata-Version: 2.1
Name: azure-cli-testsdk
Version: 0.3.0
Summary: Microsoft Azure Command-Line Tools Test SDK Module
Home-page: https://github.com/Azure/azure-cli
Author: Microsoft Corporation
Author-email: azpycli@microsoft.com
License: MIT
Platform: UNKNOWN
Classifier: Development Status :: 3 - Alpha
Classifier: Intended Audience :: Developers
Classifier: Programming Language :: Python
Classifier: Programming Language :: Python :: 3
Classifier: Programming Language :: Python :: 3.6
Classifier: Programming Language :: Python :: 3.7
Classifier: Programming Language :: Python :: 3.8
Classifier: Programming Language :: Python :: 3.9
Classifier: Programming Language :: Python :: 3.10
Classifier: License :: OSI Approved :: MIT License
Requires-Dist: ConfigArgParse (>=0.12.0)
Requires-Dist: jmespath
Requires-Dist: vcrpy (>=1.10.3)
Requires-Dist: pytest
